mcp_svg_animator/__init__.py
mcp_svg_animator/__main__.py
mcp_svg_animator/api.py
mcp_svg_animator/config.py
mcp_svg_animator/server.py
mcp_svg_animator/generators/__init__.py
mcp_svg_animator/generators/animations.py
mcp_svg_animator/generators/png_generator.py
mcp_svg_animator/generators/position_resolver.py
mcp_svg_animator/generators/video_generator.py
mcp_svg_animator/generators/yaml_loader.py
mcp_svg_animator/generators/specs/__init__.py
mcp_svg_animator/generators/specs/animation_spec.py
mcp_svg_animator/generators/specs/circle_spec.py
mcp_svg_animator/generators/specs/connection_spec.py
mcp_svg_animator/generators/specs/element_spec.py
mcp_svg_animator/generators/specs/ellipse_spec.py
mcp_svg_animator/generators/specs/group_spec.py
mcp_svg_animator/generators/specs/line_spec.py
mcp_svg_animator/generators/specs/path_spec.py
mcp_svg_animator/generators/specs/rectangle_spec.py
mcp_svg_animator/generators/specs/segment_specs.py
mcp_svg_animator/generators/specs/text_spec.py
mcp_svg_animator/generators/specs/transform_animation_spec.py
mcp_svg_animator-0.5.0.dist-info/licenses/LICENSE
mcp_svg_animator-0.5.0.dist-info/METADATA
mcp_svg_animator-0.5.0.dist-info/WHEEL
mcp_svg_animator-0.5.0.dist-info/top_level.txt
mcp_svg_animator-0.5.0.dist-info/RECORD
