Metadata-Version: 2.4
Name: mcp-svg-animator
Version: 0.5.0
Summary: An MCP server for creating svg animations.
Author-email: Romilly Cocking <romilly.cocking@gmail.com>
License-Expression: MIT
Project-URL: Homepage, https://github.com/romilly/mcp-svg-animator
Project-URL: Repository, https://github.com/romilly/mcp-svg-animator.git
Project-URL: Issues, https://github.com/romilly/mcp-svg-animator/issues
Classifier: Development Status :: 3 - Alpha
Classifier: Intended Audience :: Developers
Classifier: Programming Language :: Python :: 3
Classifier: Programming Language :: Python :: 3.10
Classifier: Programming Language :: Python :: 3.11
Classifier: Programming Language :: Python :: 3.12
Requires-Python: >=3.10
License-File: LICENSE
Requires-Dist: mcp>=1.0.0
Requires-Dist: pydantic>=2.0.0
Requires-Dist: PyYAML>=6.0
Requires-Dist: playwright>=1.40.0
Requires-Dist: drawsvg>=2.0.0
Provides-Extra: test
Requires-Dist: pytest>=7.0.0; extra == "test"
Requires-Dist: pytest-cov; extra == "test"
Requires-Dist: pyright; extra == "test"
Requires-Dist: PyHamcrest; extra == "test"
Dynamic: license-file
